heliospacecraftlocation/__init__.py
heliospacecraftlocation/heliospacecraftlocation.py
heliospacecraftlocation-0.0.6.dist-info/LICENSE
heliospacecraftlocation-0.0.6.dist-info/METADATA
heliospacecraftlocation-0.0.6.dist-info/WHEEL
heliospacecraftlocation-0.0.6.dist-info/top_level.txt
heliospacecraftlocation-0.0.6.dist-info/RECORD
