Metadata-Version: 2.1
Name: heliospacecraftlocation
Version: 0.0.6
Summary: Get HEE Coordinates for spacecraft around the Sun
Home-page: UNKNOWN
Author: Luis Alberto Canizares
Author-email: <canizares@cp.dias.ie>
License: UNKNOWN
Keywords: python,solar,nasa,esa,spacecraft,coordinates,sun,corona,parker,solar orbiter
Platform: UNKNOWN
Classifier: Development Status :: 3 - Alpha
Classifier: Intended Audience :: Developers
Classifier: Programming Language :: Python :: 3
Classifier: Operating System :: Unix
Classifier: Operating System :: MacOS :: MacOS X
Classifier: Operating System :: Microsoft :: Windows
Requires-Dist: sunpy
Requires-Dist: astropy
